discord_data_storage/__init__.py
discord_data_storage/discord_data_storage.py
discord_data_storage-0.1.0.dist-info/LICENSE
discord_data_storage-0.1.0.dist-info/METADATA
discord_data_storage-0.1.0.dist-info/WHEEL
discord_data_storage-0.1.0.dist-info/top_level.txt
discord_data_storage-0.1.0.dist-info/RECORD
